LICENSE.md
README.md
pyproject.toml
setup.cfg
setup.py
wmipa/__init__.py
wmipa/log.py
wmipa/praiseinference.py
wmipa/praiselang.py
wmipa/utils.py
wmipa/weightconverter.py
wmipa/weights.py
wmipa/wmi.py
wmipa/wmiexception.py
wmipa/wmivariables.py
wmipa/integration/__init__.py
wmipa/integration/cache_integrator.py
wmipa/integration/command_line_integrator.py
wmipa/integration/expression.py
wmipa/integration/integrand.py
wmipa/integration/integrator.py
wmipa/integration/latte_integrator.py
wmipa/integration/polynomial.py
wmipa/integration/polytope.py
wmipa/integration/symbolic_integrator.py
wmipa/integration/sympy2pysmt.py
wmipa/integration/volesti_integrator.py
wmipa_test.egg-info/PKG-INFO
wmipa_test.egg-info/SOURCES.txt
wmipa_test.egg-info/dependency_links.txt
wmipa_test.egg-info/not-zip-safe
wmipa_test.egg-info/requires.txt
wmipa_test.egg-info/top_level.txt